<?xml version="1.0" encoding="utf-8"?>
<Dokument id="id236cb14d-e001-4ed8-a65d-8a6f6a056709" SchemaLocation="http://www.retsinformation.dk/offentlig/xml/schemas/2015/06/22/LBKH.Retsinfo.LexDania_2.1.xsd">
  <Meta id="id868a42ba-188d-4ac9-a246-450b50d673d2">
    <DocumentType>LBK H#LOKDOK03</DocumentType>
    <Rank>A</Rank>
    <AccessionNumber>A20150169629</AccessionNumber>
    <DocumentId>CK000199</DocumentId>
    <UniqueDocumentId>175255</UniqueDocumentId>
    <DocumentTitle>Bekendtgørelse af lov om støtte til miljøforbedrende investeringer i mindre landbrug m.v.</DocumentTitle>
    <Year>2015</Year>
    <DiesSigni>2015-12-14</DiesSigni>
    <DateOfSubmit id="submit_1" />
    <EndDate REFid="submit_1">2016-08-17</EndDate>
    <Status>Historic</Status>
    <Number>1696</Number>
    <AendresAf>
      <Dokument>
        <KortNavn>LOV nr 628 af 08/06/2016 </KortNavn>
        <Overskrift>Senere ændringer til forskriften</Overskrift>
      </Dokument>
      <Dokument>
        <KortNavn>LBK nr 785 af 23/06/2016</KortNavn>
      </Dokument>
    </AendresAf>
    <DokumentKortNavn>LBK nr 1696 af 14/12/2015</DokumentKortNavn>
    <AnnouncedIn>Lovtidende A</AnnouncedIn>
    <DateOfHistoricMark>2016-06-24</DateOfHistoricMark>
    <Change id="change_1" />
    <Ref_Accn REFid="change_1">A20160062830</Ref_Accn>
    <Ref_Af REFid="change_1">2016-06-08</Ref_Af>
    <Ref_Text REFid="change_1">Lov om ændring af lov om Udbetaling Danmark og forskellige andre love (Overførsel af opgaver fra Statens Administrations Finansservicecenter m.fl. til Udbetaling Danmark m.v.)</Ref_Text>
    <Republished>Nej</Republished>
    <Sign id="sign" />
    <Signature REFid="sign">Eva Kjer Hansen</Signature>
    <Sub-Sign id="subsign" />
    <Signature REFid="subsign">Jette Petersen</Signature>
    <PlaceOfSignature>Miljø- og Fødevareministeriet</PlaceOfSignature>
    <JournalNumber>Miljø- og Fødevaremin.,\nNaturErhvervstyrelsen, j.nr. 15-0122-000020</JournalNumber>
    <Ministry>Miljø- og Fødevareministeriet</Ministry>
  </Meta>
  <TitelGruppe id="id5c1e993c-6006-46e5-8e2b-dc843f3afafe">
    <Titel id="idc889542f-769b-4bd7-acb1-72394cd245e5">
      <Linea>
        <Char>Bekendtgørelse af lov om støtte til miljøforbedrende investeringer i mindre landbrug m.v.</Char>
      </Linea>
    </Titel>
  </TitelGruppe>
  <DokumentIndhold id="idf3320033-ad01-446c-ad0e-e857a70d4f62">
    <Indledning id="id14e51a4b-00f7-41a7-b02d-2c268cb33219">
      <Exitus>
        <Linea>
          <Char>Herved bekendtgøres lov om støtte til miljøforbedrende investeringer i mindre landbrug m.v., jf. lovbekendtgørelse 1172 af 16. december 1992, med de ændringer, følger af § 7 i lov nr. 284 af 27. april 1994, § 1 i lov nr. 1108 af 21. december 1994, § 35 i lov nr. 430 af 6. juni 2005, § 41 i lov nr. 431 af 6. juni 2005 og § 64 i lov nr. 1336 af 19. december 2008.</Char>
        </Linea>
      </Exitus>
    </Indledning>
    <Bog id="id682bec27-89fa-4f59-b136-dd742f82c807">
      <Afsnit id="idcd09ed25-d17f-4de5-9eab-283c94123012" localId="1">
        <Kapitel id="id289dbd86-bb10-4d62-a457-b4b4100fe921" localId="1">
          <Explicatus>Kapitel 1</Explicatus>
          <Rubrica id="ida29a9c44-65ae-46ed-a6a2-8948dac880c7">
            <Linea>
              <Char>Lovens område</Char>
            </Linea>
          </Rubrica>
          <ParagrafGruppe>
            <Paragraf id="id5f2b4f96-7bbb-4747-bf8f-275dc35452cc" localId="1">
              <Explicatus>§ 1.</Explicatus>
              <Stk id="id19a36997-0490-4f3c-a732-d3ae09db7e4f">
                <Exitus>
                  <Linea>
                    <Char>Støtte efter denne lov kan ydes til investeringer i anlæg til opbevaring af husdyrgødning, der er nødvendige til opfyldelse af lovgivningens krav til udbringning, udnyttelse og opbevaring af husdyrgødning fra landbrug og andre virksomheder med husdyrhold.</Char>
                  </Linea>
                  <Linea>
                    <Char>Endvidere kan støtte ydes til anlæg, der medfører en større opbevaringskapacitet, end hvad der er nødvendigt for at opfylde lovgivningens krav til udbringning og udnyttelse af husdyrgødning.</Char>
                  </Linea>
                </Exitus>
              </Stk>
              <Stk id="iddc579e03-33c3-44bc-81e2-48b5f5df8ab2">
                <Explicatus>Stk. 2.</Explicatus>
                <Exitus>
                  <Linea>
                    <Char>Miljø- og fødevareministeren</Char>
                  </Linea>
                  <Nota id="idb42117bb-fd6f-46cd-9679-4ed870eece66">
                    <Explicatus>1)</Explicatus>
                    <Exitus>
                      <Linea>
                        <Char>Ved kongelig resolution af 28. juni 2015 blev Miljøministeriet og Ministeriet for Fødevarer, Landbrug og Fiskeri sammenlagt til et Miljø- og Fødevareministerium, jf. bekendtgørelse nr. 1229 af 3. november 2015 om ændring i forretningernes fordeling mellem ministrene.</Char>
                      </Linea>
                    </Exitus>
                  </Nota>
                  <Linea>
                    <Char>kan fastsætte regler om støtte til investeringer i andre anlæg med tilknytning til landbruget.</Char>
                  </Linea>
                </Exitus>
              </Stk>
              <Stk id="id9c34aee8-480b-4d04-8f4f-5c9ab726cd57">
                <Explicatus>Stk. 3.</Explicatus>
                <Exitus>
                  <Linea>
                    <Char>Der kan ikke ydes støtte til virksomheder, der ejes af det offentlige.</Char>
                  </Linea>
                  <Linea>
                    <Char>Dette gælder dog ikke for fælles biogasanlæg samt præstegårde.</Char>
                  </Linea>
                </Exitus>
              </Stk>
            </Paragraf>
          </ParagrafGruppe>
        </Kapitel>
        <Kapitel id="id145261e7-74ed-4820-bc8b-c2f98fec1d05" localId="2">
          <Explicatus>Kapitel 2</Explicatus>
          <Rubrica id="id0e1de619-be6b-493d-848b-616c474969c7">
            <Linea>
              <Char>Betingelser for støtte m.v.</Char>
            </Linea>
          </Rubrica>
          <ParagrafGruppe>
            <Paragraf id="id12a6301f-35e4-45e9-a584-bda399472a30" localId="2">
              <Explicatus>§ 2.</Explicatus>
              <Stk id="id4747e1f4-8c49-4bd3-8064-680ae87c4d62">
                <Exitus>
                  <Linea>
                    <Char>Støtte ydes til investeringer, der påbegyndes og afsluttes i perioden fra 1. december 1985 og til 1. oktober 1995.</Char>
                  </Linea>
                </Exitus>
              </Stk>
              <Stk id="id86dc7242-dbbf-4668-b26a-45f79de5d8d7">
                <Explicatus>Stk. 2.</Explicatus>
                <Exitus>
                  <Linea>
                    <Char>Miljø- og fødevareministeren kan fastsætte regler om, at den i stk. 1 nævnte frist ikke skal gælde for opbevaringsanlæg, der har forbindelse med eller indgår i fælles biogasanlæg og andre anlæg til særlig udnyttelse af husdyrgødning, jf. § 4, stk. 2.</Char>
                  </Linea>
                </Exitus>
              </Stk>
              <Stk id="iddcaee35f-e82e-4562-bc02-a727244f71a1">
                <Explicatus>Stk. 3.</Explicatus>
                <Exitus>
                  <Linea>
                    <Char>Miljø- og fødevareministeren fastsætter regler om betingelserne for at opnå støtte til investeringer, der afsluttes inden 1. oktober 1995.</Char>
                  </Linea>
                </Exitus>
              </Stk>
            </Paragraf>
            <Paragraf id="id9ff89c1f-bb1c-42c7-bac9-397cc5485761" localId="3">
              <Explicatus>§ 3.</Explicatus>
              <Stk id="id7d1eb10c-a8bb-4629-8dcb-ec7e3724e7bd">
                <Exitus>
                  <Linea>
                    <Char>Støtte efter denne lov kan kun ydes til investeringer, hvortil der ikke kan opnås tilskud i medfør af lov nr. 198 af 9. april 1986 om støtte til forbedring af strukturen og effektiviteten i jordbruget (forbedringsloven), jf. dog stk. 2.</Char>
                  </Linea>
                  <Linea>
                    <Char>Når der meddeles afslag på ansøgning efter forbedringslovens § 3, stk. 1, nr. 5, § 3, stk. 2, eller § 5, stk. 2, nr. 3, kan der ikke udbetales støtte efter denne lov.</Char>
                  </Linea>
                </Exitus>
              </Stk>
              <Stk id="id157bed63-eb78-4797-9beb-75b2a7eaba37">
                <Explicatus>Stk. 2.</Explicatus>
                <Exitus>
                  <Linea>
                    <Char>Støtte kan ikke ydes til investeringer, der fradrages fuldt ud i den skattepligtige indkomst (straksafskrives) efter reglerne i §§ 3 A og 21 A i lov om skattemæssige afskrivninger m.v.</Char>
                  </Linea>
                </Exitus>
              </Stk>
              <Stk id="id1e191ded-fc89-4530-9e14-18271796ccc9">
                <Explicatus>Stk. 3.</Explicatus>
                <Exitus>
                  <Linea>
                    <Char>Miljø- og fødevareministeren fastsætter regler om betingelserne for at opnå støtte eller straksafskrivning som omtalt i stk. 1 og 2.</Char>
                  </Linea>
                </Exitus>
              </Stk>
            </Paragraf>
            <Paragraf id="id529e39f4-a704-4fb8-a539-ce00c1c3645a" localId="4">
              <Explicatus>§ 4.</Explicatus>
              <Stk id="ide7920bcf-889f-4724-9878-c0b23de45ba7">
                <Exitus>
                  <Linea>
                    <Char>Støtte ydes til investeringer på ansøgerens ejendom eller til investeringer, der gennemføres af flere ansøgere i fællesskab, hvis anlægget efter investeringens gennemførelse har en tilstrækkelig kapacitet til opfyldelse af lovgivningens krav om udbringning, udnyttelse og opbevaring af husdyrgødning i landbrug og andre virksomheder med husdyrhold.</Char>
                  </Linea>
                </Exitus>
              </Stk>
              <Stk id="id30b64445-b733-4963-b374-4a7a2f329b4c">
                <Explicatus>Stk. 2.</Explicatus>
                <Exitus>
                  <Linea>
                    <Char>Miljø- og fødevareministeren kan fastsætte særlige regler om støtte til</Char>
                  </Linea>
                </Exitus>
                <Exitus id="id1b036150-0dc3-4d9c-96a0-6217ccbd0d1c">
                  <Index>
                    <Indentatio id="idca5a2066-50f9-4e77-8514-04bcc46a5fb8" formaInd="Nummer">
                      <Explicatus>1)</Explicatus>
                      <Exitus>
                        <Linea>
                          <Char>fælles opbevaringsanlæg for flere ejendomme,</Char>
                        </Linea>
                      </Exitus>
                    </Indentatio>
                    <Indentatio id="id416e7d84-1932-499a-b09e-e532d3bcf304" formaInd="Nummer">
                      <Explicatus>2)</Explicatus>
                      <Exitus>
                        <Linea>
                          <Char>anlæg, der har forbindelse med eller indgår i fælles biogasanlæg, og</Char>
                        </Linea>
                      </Exitus>
                    </Indentatio>
                    <Indentatio id="id46531acd-56ac-4edb-b115-d3810eb59b1c" formaInd="Nummer">
                      <Explicatus>3)</Explicatus>
                      <Exitus>
                        <Linea>
                          <Char>andre anlæg til særlig udnyttelse af husdyrgødning.</Char>
                        </Linea>
                      </Exitus>
                    </Indentatio>
                  </Index>
                </Exitus>
              </Stk>
              <Stk id="id0b83f4fd-285b-404a-8413-513a6f7a8f10">
                <Explicatus>Stk. 3.</Explicatus>
                <Exitus>
                  <Linea>
                    <Char>Miljø- og fødevareministeren kan endvidere fastsætte særlige regler om støtte til de i § 1, stk. 2, nævnte anlæg.</Char>
                  </Linea>
                </Exitus>
              </Stk>
            </Paragraf>
            <Paragraf id="id8a8fa26e-7727-4ff7-b7c2-be9b59e6d1ba" localId="5">
              <Explicatus>§ 5.</Explicatus>
              <Stk id="idb2e25e62-2a87-48af-a6ac-0bad1b2f6bcb">
                <Exitus>
                  <Linea>
                    <Char>Der ydes støtte til ansøgerens udgifter til investeringen bortset fra udgifter til løn m.v. til ansatte hos ansøgeren.</Char>
                  </Linea>
                </Exitus>
              </Stk>
            </Paragraf>
            <Paragraf id="idb5b12a87-5d26-4a99-b973-d9f7a51d99c8" localId="6">
              <Explicatus>§ 6.</Explicatus>
              <Stk id="id8d983fab-e656-477a-b269-e05f45a298f0">
                <Exitus>
                  <Linea>
                    <Char>En investering kan kun støttes, hvis beløbet efter § 5 udgør mindst 10.000 kr.</Char>
                  </Linea>
                </Exitus>
              </Stk>
            </Paragraf>
            <Paragraf id="id3fe98004-0174-4369-8c87-f791747efb4f" localId="7">
              <Explicatus>§ 7.</Explicatus>
              <Stk id="iddbdc9398-6f04-49da-bf66-a91b2d0ced26">
                <Exitus>
                  <Linea>
                    <Char>Til investeringer, der ikke overstiger 85.000 kr., ydes støtten som et kontant tilskud.</Char>
                  </Linea>
                  <Linea>
                    <Char>Støtten udgør indtil 35 pct. af det beløb, der er opgjort efter § 5.</Char>
                  </Linea>
                  <Linea>
                    <Char>Støtte til anlæg til opbevaring af gødning m.v. efter § 4, stk. 2, kan dog udgøre mere end 35 pct., der ydes som et kontant tilskud.</Char>
                  </Linea>
                </Exitus>
              </Stk>
              <Stk id="id49f2c6d2-3571-4bd4-8d96-702ae124b7e1">
                <Explicatus>Stk. 2.</Explicatus>
                <Exitus>
                  <Linea>
                    <Char>Miljø- og fødevareministeren fastsætter nærmere regler om støttesatser og støttens beregning og udbetaling.</Char>
                  </Linea>
                </Exitus>
              </Stk>
            </Paragraf>
            <Paragraf id="id380435ce-3e4f-4c86-b724-2c2745f4821b" localId="8">
              <Explicatus>§ 8.</Explicatus>
              <Stk id="id1675366c-5da7-4797-8ea1-e51ca567b02d">
                <Exitus>
                  <Linea>
                    <Char>Til investeringer på over 85.000 kr. ydes støtte i lige store rater een gang årligt i 10 år.</Char>
                  </Linea>
                  <Linea>
                    <Char>Den kapitaliserede værdi af raterne skal svare til det støttebeløb, som var fremkommet, hvis støtten var udbetalt som et kontant tilskud efter reglerne herom i § 7.</Char>
                  </Linea>
                  <Linea>
                    <Char>Miljø- og fødevareministeren fastsætter nærmere regler herom.</Char>
                  </Linea>
                </Exitus>
              </Stk>
            </Paragraf>
            <Paragraf id="id59f00458-1972-4ab9-b9ea-ad13facd7521" localId="9">
              <Explicatus>§ 9.</Explicatus>
              <Stk id="id5430fd68-a133-4d81-955c-aa06467bde46">
                <Exitus>
                  <Linea>
                    <Char>(Ophævet)</Char>
                  </Linea>
                </Exitus>
              </Stk>
            </Paragraf>
            <Paragraf id="idc34299db-a724-4cd8-9e73-83ee389c3580" localId="10">
              <Explicatus>§ 10.</Explicatus>
              <Stk id="ide5940d87-e87a-42f7-b098-b4ce1eef911e">
                <Exitus>
                  <Linea>
                    <Char>Miljø- og fødevareministeren kan efter ansøgning yde statsgaranti for lån, der optages til investeringer, der er berettiget til støtte efter loven.</Char>
                  </Linea>
                </Exitus>
              </Stk>
              <Stk id="ide4b669cb-4ab6-4517-a308-399fa7d0f4b1">
                <Explicatus>Stk. 2.</Explicatus>
                <Exitus>
                  <Linea>
                    <Char>Ansøgning om garanti indsendes senest 31. marts 1996 til miljø- og fødevareministeren.</Char>
                  </Linea>
                  <Linea>
                    <Char>Lån, for hvilke der garanteres, kan ikke overstige 400.000 kr., og garantien kan ikke udstrækkes til mere end 15 år fra datoen for lånets optagelse.</Char>
                  </Linea>
                  <Linea>
                    <Char>Ydelse af garanti er betinget af, at ansøgeren ikke er i stand til selv at stille den sikkerhed, der kræves for optagelse af lån på det almindelige lånemarked, og at lånet sikres efter regler, der fastsættes af landbrugsministeren.</Char>
                  </Linea>
                </Exitus>
              </Stk>
              <Stk id="id787d5123-25da-482f-905b-adc770a1ed37">
                <Explicatus>Stk. 3.</Explicatus>
                <Exitus>
                  <Linea>
                    <Char>Miljø- og fødevareministeren kan fastsætte nærmere regler om ydelse af garanti, herunder om bortfald af statens garantiforpligtelse.</Char>
                  </Linea>
                </Exitus>
              </Stk>
            </Paragraf>
            <Paragraf id="idf1b6bd05-432a-4ea8-acad-cc132ba3550b" localId="11">
              <Explicatus>§ 11.</Explicatus>
              <Stk id="id29060cb8-3f0e-43bd-99d8-3d01772b1b79">
                <Exitus>
                  <Linea>
                    <Char>Støtten medregnes ikke til modtagerens skattepligtige indkomst.</Char>
                  </Linea>
                  <Linea>
                    <Char>Støtte, der ydes i rater, opgøres som den kapitaliserede værdi efter § 8.</Char>
                  </Linea>
                  <Linea>
                    <Char>Investeringsudgifter svarende til den udbetalte støtte kan ikke fradrages ved indkomstopgørelsen eller medregnes ved opgørelsen af grundlaget for skattemæssige afskrivninger og medregnes ikke til anskaffelsessummen ved opgørelsen af den skattepligtige fortjeneste ved afståelse af ejendommen.</Char>
                  </Linea>
                </Exitus>
              </Stk>
            </Paragraf>
            <Paragraf id="id1a8152f1-9254-48bb-b485-0f2c9705dbb3" localId="12">
              <Explicatus>§ 12.</Explicatus>
              <Stk id="ide64712dd-e21e-4a4a-a009-de07a585f5a8">
                <Exitus>
                  <Linea>
                    <Char>Støttebeløb til investeringer omfattet af lovens § 1, stk. 1, kan højst udgøre 150.000 kr. pr. ejendom.</Char>
                  </Linea>
                  <Linea>
                    <Char>Når støtten udbetales efter reglerne i § 8, kan den kapitaliserede værdi af raterne højst udgøre 150.000 kr. pr. ejendom.</Char>
                  </Linea>
                </Exitus>
              </Stk>
            </Paragraf>
            <Paragraf id="id88461f10-542e-44f8-b11d-f8d66f81b44d" localId="13">
              <Explicatus>§ 13.</Explicatus>
              <Stk id="id28f31ad0-c095-4f6d-afe9-66a76bb233c7">
                <Exitus>
                  <Linea>
                    <Char>Miljø- og fødevareministeren kan fastsætte nærmere regler om ydelse af støtte m.v. efter denne lov.</Char>
                  </Linea>
                </Exitus>
              </Stk>
            </Paragraf>
          </ParagrafGruppe>
        </Kapitel>
        <Kapitel id="id250a01a4-be79-48ac-ba14-cdcb79e9d6b9" localId="3">
          <Explicatus>Kapitel 3</Explicatus>
          <Rubrica id="id68e705b9-3440-40b8-be26-8eeb80eca3b7">
            <Linea>
              <Char>Administrative bestemmelser</Char>
            </Linea>
          </Rubrica>
          <ParagrafGruppe>
            <Paragraf id="idc48e4170-66f4-4c27-9c04-ea99d2058123" localId="14">
              <Explicatus>§ 14.</Explicatus>
              <Stk id="id6f289679-9140-4760-9a7b-ad43c603e2ab">
                <Exitus>
                  <Linea>
                    <Char>For at opnå støtte efter denne lov, jf. § 1, stk. 1, skal ansøgeren, inden investeringen påbegyndes, udarbejde en projektbeskrivelse, som indsendes til kommunalbestyrelsen til forhåndsvurdering.</Char>
                  </Linea>
                  <Linea>
                    <Char>Projektbeskrivelsen vedlægges en erklæring fra landbrugets konsulenttjeneste om den tilstrækkelige kapacitet samt om, at opbevaringsanlægget, hvortil der søges om tilskud, tillige med eventuelt allerede etablerede anlæg har en kapacitet, der er i overensstemmelse med tilstrækkelig kapacitet.</Char>
                  </Linea>
                </Exitus>
              </Stk>
              <Stk id="id5abc320d-af77-4036-b60e-c750dbcb4fa0">
                <Explicatus>Stk. 2.</Explicatus>
                <Exitus>
                  <Linea>
                    <Char>Ved forhåndsvurderingen attesterer kommunalbestyrelsen, at de projekterede anlæg opfylder kapacitetskravene i § 4, stk. 1, samt de krav om indretning af anlæggene, som er fastsat i regler udstedt i medfør af miljøbeskyttelsesloven eller ved afgørelser i henhold hertil.</Char>
                  </Linea>
                </Exitus>
              </Stk>
              <Stk id="id972349ef-b29d-4348-9665-fec5235298ed">
                <Explicatus>Stk. 3.</Explicatus>
                <Exitus>
                  <Linea>
                    <Char>Det forhåndsvurderede projekt indsendes til jordbrugskommissionen, som videresender dette til NaturErhvervstyrelsen sammen med en forbedringsplan, udarbejdet efter lov nr. 198 af 9. april 1986 om støtte til forbedring af strukturen og effektiviteten i jordbruget, eller andet af Jordbrugsdirektoratet godkendt ansøgningsskema.</Char>
                  </Linea>
                  <Linea>
                    <Char>Hvis betingelserne for at opnå forbedringsstøtte ikke er opfyldt, attesteres dette af Jordbrugsdirektoratet.</Char>
                  </Linea>
                  <Linea>
                    <Char>Investeringen må ikke påbegyndes, før Jordbrugsdirektoratets afgørelse herom foreligger.</Char>
                  </Linea>
                </Exitus>
              </Stk>
              <Stk id="idd5ea8226-a119-47e7-8b97-f822613b59f5">
                <Explicatus>Stk. 4.</Explicatus>
                <Exitus>
                  <Linea>
                    <Char>Miljø- og fødevareministeren kan fastsætte nærmere regler om den i stk. 1-3 fastsatte ordning, herunder om anvendelse af særlige skemaer samt om, hvilke oplysninger der skal tilvejebringes til brug for forhåndsvurderingen.</Char>
                  </Linea>
                </Exitus>
              </Stk>
              <Stk id="idc73fd624-21b9-47ee-b425-1e8c96f99730">
                <Explicatus>Stk. 5.</Explicatus>
                <Exitus>
                  <Linea>
                    <Char>Miljø- og fødevareministeren fastsætter nærmere regler om opnåelse af støtte til investeringer omfattet af § 1, stk. 2, og § 4, stk. 2.</Char>
                  </Linea>
                </Exitus>
              </Stk>
            </Paragraf>
            <Paragraf id="id82570f46-1d37-4252-b9d1-407f5b279b2f" localId="15">
              <Explicatus>§ 15.</Explicatus>
              <Stk id="id1e4193ab-0c53-4737-ac3c-853007c422da">
                <Exitus>
                  <Linea>
                    <Char>Når investeringen er afsluttet, indsendes ansøgning om støtte til kommunalbestyrelsen.</Char>
                  </Linea>
                  <Linea>
                    <Char>Ansøgningen om støtte skal være ledsaget af den i § 14, stk. 3, nævnte attestation fra NaturErhvervstyrelsen.</Char>
                  </Linea>
                </Exitus>
              </Stk>
              <Stk id="id20a03098-0e83-4411-ac74-65ca4fd56564">
                <Explicatus>Stk. 2.</Explicatus>
                <Exitus>
                  <Linea>
                    <Char>Ansøgningen skal indeholde dokumentation for de udgifter, der er medgået til investeringen, med attest af en statsautoriseret eller registreret revisor eller en landbrugskonsulent i driftsøkonomi.</Char>
                  </Linea>
                </Exitus>
              </Stk>
              <Stk id="idef3342e9-9d4e-467b-a6f6-8bd8e62bba6a">
                <Explicatus>Stk. 3.</Explicatus>
                <Exitus>
                  <Linea>
                    <Char>Ansøgning om støtte skal være indsendt til kommunalbestyrelsen senest den 31. marts 1996.</Char>
                  </Linea>
                </Exitus>
              </Stk>
            </Paragraf>
            <Paragraf id="id073df3a4-28b5-4ed6-88d6-c4f2c891435c" localId="16">
              <Explicatus>§ 16.</Explicatus>
              <Stk id="id363e3c21-6d51-45ab-bb79-10de7d99a698">
                <Exitus>
                  <Linea>
                    <Char>Kommunalbestyrelsen træffer afgørelse i sager om støtte, jf. dog stk. 2.</Char>
                  </Linea>
                </Exitus>
              </Stk>
              <Stk id="id6a07c771-d156-4700-9fda-22b3531df80d">
                <Explicatus>Stk. 2.</Explicatus>
                <Exitus>
                  <Linea>
                    <Char>Miljø- og fødevareministeren træffer afgørelse i sager vedrørende § 1, stk. 2, og § 4, stk. 2.</Char>
                  </Linea>
                  <Linea>
                    <Char>Miljø- og fødevareministeren kan fastsætte regler om at afgørelser i visse af disse sager træffes af kommunalbestyrelsen.</Char>
                  </Linea>
                </Exitus>
              </Stk>
            </Paragraf>
            <Paragraf id="id142260b6-5111-432e-824c-218473298119" localId="17">
              <Explicatus>§ 17.</Explicatus>
              <Stk id="ide553a071-a177-4daf-b8c5-0d5c60616001">
                <Exitus>
                  <Linea>
                    <Char>Støtte efter loven udbetales af miljø- og fødevareministeren inden for beløbsrammer fastsat på de årlige finanslove.</Char>
                  </Linea>
                  <Linea>
                    <Char>Den del af en beløbsramme, der ikke er udnyttet i finansåret, kan overføres til følgende finansår.</Char>
                  </Linea>
                </Exitus>
              </Stk>
            </Paragraf>
            <Paragraf id="ideca4a743-d0e2-41bf-92f7-cd72990e8321" localId="18">
              <Explicatus>§ 18.</Explicatus>
              <Stk id="id3748ab66-4336-44bc-b197-760ab2b3b031">
                <Exitus>
                  <Linea>
                    <Char>Miljø- og fødevareministeren kan fastsætte nærmere regler om behandlingen af sagerne, herunder om ansøgningens form og indhold og om, hvilke oplysninger kommunalbestyrelsen skal tilvejebringe i forbindelse med sagens behandling.</Char>
                  </Linea>
                </Exitus>
              </Stk>
            </Paragraf>
            <Paragraf id="ide7244813-78d4-4491-8e45-6625eb1dd305" localId="19">
              <Explicatus>§ 19.</Explicatus>
              <Stk id="idefe648b7-9edd-4656-bbdb-c7f60c656f85">
                <Exitus>
                  <Linea>
                    <Char>Miljø- og fødevareministeren kan bemyndige NaturErhvervstyrelsen og Kongeriget Danmarks Hypotekbank og Finansforvaltning (Hypotekbanken) til at udøve beføjelser, der i denne lov er tillagt ministeren.</Char>
                  </Linea>
                </Exitus>
              </Stk>
            </Paragraf>
            <Paragraf id="idc9f6dd05-92bc-4e1b-a690-4591138d2335" localId="20">
              <Explicatus>§ 20.</Explicatus>
              <Stk id="id451cad60-b387-4462-a5d2-bd0933ed52b5">
                <Exitus>
                  <Linea>
                    <Char>Miljø- og fødevareministeren kan bestemme, at tilsagn om støtte efter denne lov skal bortfalde helt eller delvis, og at udbetalt tilskud skal tilbagebetales helt eller delvis, hvis ansøgeren har afgivet urigtige eller vildledende oplysninger eller har fortiet oplysninger af betydning for støtten, eller hvis ansøgeren ikke længere opfylder betingelserne for støtte.</Char>
                  </Linea>
                </Exitus>
              </Stk>
              <Stk id="id8e019536-97d0-47cc-81bd-10f399e63904">
                <Explicatus>Stk. 2.</Explicatus>
                <Exitus>
                  <Linea>
                    <Char>Miljø- og fødevareministeren eller den, ministeren bemyndiger hertil, har til enhver tid uden retskendelse og mod behørig legitimation adgang til de bedrifter m.m., hvortil der er ydet støtte efter denne lov, for at foretage eftersyn af bedriften m.m. samt af regnskaber og forretningsbøger m.m.</Char>
                  </Linea>
                </Exitus>
              </Stk>
            </Paragraf>
            <Paragraf id="id3e8f629e-4e38-4574-904e-3d20936c0a4c" localId="21">
              <Explicatus>§§ 20 a-20 b.</Explicatus>
              <Stk id="id998ab033-91df-4032-a9ca-c1ff351fcbc6">
                <Exitus>
                  <Linea>
                    <Char>(Ophævet)</Char>
                  </Linea>
                </Exitus>
              </Stk>
            </Paragraf>
          </ParagrafGruppe>
        </Kapitel>
        <Kapitel id="idcddcd5fa-e1c9-41d9-a950-37912c7fcfaa" localId="4">
          <Explicatus>Kapitel 4</Explicatus>
          <Rubrica id="idf5e36647-609a-4e1c-a6e1-b16ec0032f1e">
            <Linea>
              <Char>Klagebestemmelser</Char>
            </Linea>
          </Rubrica>
          <ParagrafGruppe>
            <Paragraf id="id1ede74f2-fc88-478c-9229-a97fe93113e6" localId="22">
              <Explicatus>§ 21.</Explicatus>
              <Stk id="idd3f5963e-6978-4b04-8601-46018da99533">
                <Exitus>
                  <Linea>
                    <Char>Kommunalbestyrelsens afgørelser i forbindelse med forhåndsvurdering, jf. § 14, om, at kapacitetskravet, jf. § 4, stk. 1, ikke er opfyldt, kan af ansøgeren påklages til miljø- og fødevareministeren.</Char>
                  </Linea>
                </Exitus>
              </Stk>
              <Stk id="idce994339-6796-4afe-bf04-f2451ba6e768">
                <Explicatus>Stk. 2.</Explicatus>
                <Exitus>
                  <Linea>
                    <Char>Kommunalbestyrelsens afgørelser efter § 16 om støtte kan af ansøgeren påklages til miljø- og fødevareministeren.</Char>
                  </Linea>
                </Exitus>
              </Stk>
              <Stk id="id8f345bd8-40d5-4013-8604-fda594b654a0">
                <Explicatus>Stk. 3.</Explicatus>
                <Exitus>
                  <Linea>
                    <Char>For kommunalbestyrelsens afgørelse efter stk. 1 og 2 er klagefristen 4 uger fra den dag, afgørelsen er meddelt ansøgeren.</Char>
                  </Linea>
                </Exitus>
              </Stk>
              <Stk id="id48520e78-ca4b-460e-8642-f938f7d70b07">
                <Explicatus>Stk. 4.</Explicatus>
                <Exitus>
                  <Linea>
                    <Char>Miljø- og fødevareministeren kan fastsætte regler om adgang til at klage over afgørelser, der er truffet i henhold til en bemyndigelse efter § 19, herunder at afgørelser ikke kan indbringes for anden administrativ myndighed.</Char>
                  </Linea>
                </Exitus>
              </Stk>
            </Paragraf>
          </ParagrafGruppe>
        </Kapitel>
        <Kapitel id="id27737112-931c-44fd-b9ad-4465eb471322" localId="5">
          <Explicatus>Kapitel 5</Explicatus>
          <Rubrica id="id5cecb5da-ddae-48d0-8207-231aa050a2ee">
            <Linea>
              <Char>Kortlægning m.v.</Char>
            </Linea>
          </Rubrica>
          <ParagrafGruppe>
            <Paragraf id="id5dda581d-9805-445c-a168-8e2cd48522b3" localId="23">
              <Explicatus>§ 22.</Explicatus>
              <Stk id="id17ce2cca-7972-43d9-b322-8286f3d98636">
                <Exitus>
                  <Linea>
                    <Char>Kommunalbestyrelsen skal foranledige en kortlægning af den eksisterende og forventede husdyrgødningsmængde for landbrugsejendomme m.v. i kommunen.</Char>
                  </Linea>
                </Exitus>
              </Stk>
              <Stk id="id7545ef2c-786b-4fc3-98ce-a3f2caff52b8">
                <Explicatus>Stk. 2.</Explicatus>
                <Exitus>
                  <Linea>
                    <Char>På baggrund af kortlægningen udarbejder kommunalbestyrelsen en vejledende plan om etablering af fælles opbevaringsanlæg og fælles biogasanlæg.</Char>
                  </Linea>
                  <Linea>
                    <Char>Den vejledende plan bør endvidere indeholde kommunens overvejelser om etablering af kommunale fælles biogasanlæg og dermed indpasning i den generelle varmeforsyning i kommunen.</Char>
                  </Linea>
                </Exitus>
              </Stk>
              <Stk id="id8d1153c5-04cc-4ca6-a23d-8faa456f4234">
                <Explicatus>Stk. 3.</Explicatus>
                <Exitus>
                  <Linea>
                    <Char>Producenter af husdyrgødning skal efter anmodning fra kommunalbestyrelsen meddele denne de oplysninger, der findes nødvendige for kortlægning, planlægning og etablering af kommunale fælles biogasanlæg.</Char>
                  </Linea>
                </Exitus>
              </Stk>
            </Paragraf>
          </ParagrafGruppe>
        </Kapitel>
        <Kapitel id="id3411aa39-21aa-4ecb-a183-926c9fb142c1" localId="6">
          <Explicatus>Kapitel 6</Explicatus>
          <Rubrica id="ide00c161f-7e60-47df-b32d-97bc6582625a">
            <Linea>
              <Char>Straffebestemmelser</Char>
            </Linea>
          </Rubrica>
          <ParagrafGruppe>
            <Paragraf id="id1694ff90-77e2-46bd-acf9-ba6344b42c21" localId="24">
              <Explicatus>§ 22 a.</Explicatus>
              <Stk id="idac6aff43-5618-4cea-9153-bf928154986d">
                <Exitus>
                  <Linea>
                    <Char>Den, der til brug for afgørelser, der træffes i henhold til denne lov eller de i medfør af loven fastsatte regler, giver urigtige eller vildledende oplysninger eller fortier oplysninger af betydning for afgørelsen, straffes med bøde, medmindre højere straf er forskyldt efter anden lovgivning.</Char>
                  </Linea>
                  <Linea>
                    <Char>Det samme gælder den, der handler i strid med vilkår, der er fastsat i en sådan afgørelse, eller som forsøger herpå.</Char>
                  </Linea>
                </Exitus>
              </Stk>
              <Stk id="id99aff807-0eb5-40de-a9e3-91460378d649">
                <Explicatus>Stk. 2.</Explicatus>
                <Exitus>
                  <Linea>
                    <Char>Undladelse af at give oplysninger som nævnt i § 22, stk. 3, straffes med bøde.</Char>
                  </Linea>
                </Exitus>
              </Stk>
              <Stk id="id637c5822-b353-44ce-9f5d-692c29ad9994">
                <Explicatus>Stk. 3.</Explicatus>
                <Exitus>
                  <Linea>
                    <Char>Er overtrædelsen begået af et aktieselskab, anpartsselskab, andelsselskab eller lignende, kan der pålægges selskabet som sådant bødeansvar.</Char>
                  </Linea>
                </Exitus>
              </Stk>
            </Paragraf>
          </ParagrafGruppe>
        </Kapitel>
        <Kapitel id="id26bcef37-729f-4940-946b-de6d0f9a2f91" localId="7">
          <Explicatus>Kapitel 7</Explicatus>
          <Rubrica id="iddd6ed0c6-f483-4c17-a403-5182f9342341">
            <Linea>
              <Char>Ikrafttrædelsesbestemmelser m.v.</Char>
            </Linea>
          </Rubrica>
          <ParagrafGruppe>
            <Paragraf id="id40ae0725-8121-457d-97ee-94c6b6ef2699" localId="25">
              <Explicatus>§ 23.</Explicatus>
              <Stk id="id8d49d291-8c20-4001-8168-3fb44916bf0d">
                <Exitus>
                  <Linea>
                    <Char>Tidspunktet for lovens ikrafttræden fastsættes af miljø- og fødevareministeren.</Char>
                  </Linea>
                  <Nota id="id396575a9-d29b-410e-a6c3-5c2897a6fc23">
                    <Explicatus>2)</Explicatus>
                    <Exitus>
                      <Linea>
                        <Char>Loven er trådt i kraft den 1. april 1987, jf. bekendtgørelse nr. 127 af 16. marts 1987.</Char>
                      </Linea>
                    </Exitus>
                  </Nota>
                </Exitus>
              </Stk>
            </Paragraf>
            <Paragraf id="id8ff3fd03-e7a6-4ca5-bb8a-6e35658789a1" localId="26">
              <Explicatus>§ 24.</Explicatus>
              <Stk id="id598ef23d-4ad3-424e-899e-073ae0d9b9c9">
                <Exitus>
                  <Linea>
                    <Char>Loven gælder ikke for Færøerne og Grønland.</Char>
                  </Linea>
                </Exitus>
              </Stk>
            </Paragraf>
          </ParagrafGruppe>
        </Kapitel>
      </Afsnit>
    </Bog>
    <Ikraft id="id24808e5f-2901-4ec8-9e1e-c92c9a27973c">
      <Exitus>
        <Linea>
          <Char>Lov nr. 392 af 10. juni 1987 om ændring af lov om miljøbeskyttelse og lov om støtte til miljøforbedrende investeringer i mindre landbrug m.v., der vedrører § 2, stk. 1, § 3, stk. 4, § 4, stk. 1, § 5, stk. 2, § 7 stk. 2-4, § 10, stk. 2, § 14, stk. 2-7 og § 15, stk. 3, indeholder følgende ikrafttrædelsesbestemmelser og overgangsregler:</Char>
        </Linea>
      </Exitus>
      <IkraftCentreretParagraf id="idf53d79dc-6842-4c1b-9eed-4b1894c34bbe">
        <Explicatus>§ 3</Explicatus>
        <Stk id="id52ffc8df-265e-4bc0-999f-b37c26e656b7">
          <Explicatus>Stk. 1.</Explicatus>
          <Exitus>
            <Linea>
              <Char>Loven træder i kraft dagen efter bekendtgørelsen i Lovtidende.</Char>
            </Linea>
            <Nota id="id72bb5421-b576-4b7d-a137-0d38079dcddb">
              <Explicatus>3)</Explicatus>
              <Exitus>
                <Linea>
                  <Char>Lov nr. 16 af 14. januar 1987 er trådt i kraft den 1. april 1987, og lov nr. 392 af 10. juni 1987 er trådt i kraft den 18. juni 1987.</Char>
                </Linea>
              </Exitus>
            </Nota>
          </Exitus>
        </Stk>
        <Stk id="id52d1f0fc-5a9f-49be-975c-5c30b7da6b0f">
          <Explicatus>Stk. 2.</Explicatus>
          <Exitus>
            <Linea>
              <Char>Reglerne i § 2,</Char>
            </Linea>
            <Nota id="idab567e35-e694-40ca-b500-9daf26f85189">
              <Explicatus>4)</Explicatus>
              <Exitus>
                <Linea>
                  <Char>§ 2 i lov nr. 392 af 10. juni 1987 indeholder ændringerne til lov nr. 16 af 14. januar 1987 om støtte til miljøforbedrende investeringer i mindre landbrug m.v., nr. 2 indeholder ændringen til § 3, stk. 4 og nr. 12 indeholder ændringen til § 14, stk. 7, som bliver stk. 6.</Char>
                </Linea>
              </Exitus>
            </Nota>
            <Linea>
              <Char>bortset fra nr. 2 og nr. 12, har virkning for de investeringer om hvilke forhåndsanmeldelse eller ansøgning om forhåndsvurdering er modtaget af kommunalbestyrelsen efter den 18. maj 1987.</Char>
            </Linea>
            <Linea>
              <Char>Tilsvarende gælder for de investeringer, hvortil Jordbrugsdirektoratet efter dette tidspunkt har meddelt tilladelse til igangsætning.</Char>
            </Linea>
          </Exitus>
        </Stk>
        <Stk id="idb60426e1-16aa-4da9-9d69-c4ba3a9757ac">
          <Explicatus>Stk. 3.</Explicatus>
          <Exitus>
            <Linea>
              <Char>Er bindende aftale om levering af et gødningsopbevaringsanlæg indgået inden den 19. maj 1987, kan støtte ydes efter hidtil gældende regler, uanset bestemmelsen i stk. 2.</Char>
            </Linea>
          </Exitus>
        </Stk>
      </IkraftCentreretParagraf>
      <IkraftCentreretParagraf id="ide002240e-44d6-44df-9def-cbc8293188bc">
        <Explicatus>§ 4</Explicatus>
        <Stk id="id54a9559f-abb0-4a09-a5ac-00a15e553c57">
          <Explicatus>Stk. 1.</Explicatus>
          <Exitus>
            <Linea>
              <Char>For investeringer, der gennemføres efter hidtidige gældende regler, skal ansøgning om støtte være indgivet til kommunalbestyrelsen senest den 31. december 1988.</Char>
            </Linea>
          </Exitus>
        </Stk>
        <Stk id="id89980305-0d19-450f-94e9-dc34fca4081f">
          <Explicatus>Stk. 2.</Explicatus>
          <Exitus>
            <Linea>
              <Char>Miljøministeren kan fastsætte overgangsregler og herunder fastsætte i hvilket omfang regler, der er fastsat i medfør af de hidtil gældende regler, opretholdes.</Char>
            </Linea>
          </Exitus>
        </Stk>
      </IkraftCentreretParagraf>
    </Ikraft>
    <Ikraft id="idcef82e52-7454-4f04-9dd3-e8591d9c3288">
      <Exitus>
        <Linea>
          <Char>Lov nr. 380 af 6. juni 1991 om ændring af forskellige lovbestemmelser om inddrivelse af offentlige fordringer (Lønindholdelse m.v.) indeholder følgende ikrafttrædelsesbestemmelse:</Char>
        </Linea>
      </Exitus>
      <IkraftCentreretParagraf id="id805a7142-8712-4046-a1f8-0d3bf181bdaf">
        <Explicatus>§ 33</Explicatus>
        <Stk id="id5033259c-b06e-40d7-98c4-436e9c42b596">
          <Exitus>
            <Linea>
              <Char>Loven træder i kraft ved bekendtgørelse i Lovtidende og finder også anvendelse på fordringer forfaldne før lovens ikrafttræden.</Char>
            </Linea>
            <Nota id="ida646acfb-83d5-48f2-95f2-5093c8e8cf4e">
              <Explicatus>5)</Explicatus>
              <Exitus>
                <Linea>
                  <Char>Lov nr. 380 af 6. juni 1991 er offentliggjort i Lovtidende og trådt i kraft den 7. juni 1991.</Char>
                </Linea>
              </Exitus>
            </Nota>
          </Exitus>
        </Stk>
      </IkraftCentreretParagraf>
    </Ikraft>
    <Ikraft id="id095ef110-707e-470b-9a35-d2f8d9e1f819">
      <Exitus>
        <Linea>
          <Char>Lov nr. 339 af 14. maj 1992 om ændring af lov om støtte til miljøforbedrende investeringer i mindre landbrug m.v. og lov om ændring af lov om skattemæssige afskrivninger m.v. (Miljøstøtteloven) indeholder følgende ikrafttrædelsesbestemmelser og overgangsregler:</Char>
        </Linea>
      </Exitus>
      <IkraftCentreretParagraf id="id062b3264-ebaa-4ba5-964a-c25101bc5826">
        <Explicatus>§ 3</Explicatus>
        <Stk id="id0d0038b2-1d89-454d-ae51-9668f55269b1">
          <Explicatus>Stk. 1.</Explicatus>
          <Exitus>
            <Linea>
              <Char>Landbrugsministeren fastsætter tidspunktet for lovens ikrafttræden.</Char>
            </Linea>
            <Nota id="id5ee18ffb-7d69-49f5-b424-b5453c02acf8">
              <Explicatus>6)</Explicatus>
              <Exitus>
                <Linea>
                  <Char>Loven er trådt i kraft den 1. januar 1993, jf. bekendtgørelse nr. 966 af 10. december 1992.</Char>
                </Linea>
              </Exitus>
            </Nota>
          </Exitus>
        </Stk>
        <Stk id="id4a006b92-9153-4678-86e8-baf5e1e5852e">
          <Explicatus>Stk. 2.</Explicatus>
          <Exitus>
            <Linea>
              <Char>Landbrugsministeren kan fastsætte regler om, at der i en overgangsperiode, indtil ændrede regler om udbringning og udnyttelse af husdyrgødning er fastsat, kan ydes tilskud til anlæg, hvis opbevaringskapacitet er mindst 9 måneder.</Char>
            </Linea>
            <Linea>
              <Char>For ejendomme med kvæg, der går ude om sommeren, kan landbrugsministeren fastsætte regler om, at der kan ydes tilskud til anlæg med mindst 7 måneders opbevaringskapacitet.</Char>
            </Linea>
          </Exitus>
        </Stk>
      </IkraftCentreretParagraf>
    </Ikraft>
    <Ikraft id="idf8e01f8f-a4f0-416a-aa2a-1a2f75e5969c">
      <Exitus>
        <Linea>
          <Char>Lov nr. 284 af 27. april 1994 om ændring af forskellige lovbestemmelser om inddrivelse af statskrav (Lønindeholdelse og modregning i visse erhvervs- og miljøtilskud)</Char>
        </Linea>
        <Nota id="id6f282103-2164-409f-833a-00aba6de60ed">
          <Explicatus>7)</Explicatus>
          <Exitus>
            <Linea>
              <Char>Lovændringen vedrører ændring af § 20 a, stk. 1, og indsættelse af § 21, stk. 5, 2. pkt.</Char>
            </Linea>
          </Exitus>
        </Nota>
        <Linea>
          <Char>indeholder følgende ikrafttrædelses- og overgangsbestemmelse:</Char>
        </Linea>
      </Exitus>
      <IkraftCentreretParagraf id="idd6c44ec2-6c7d-4f97-9633-9e3dfe05db4a">
        <Explicatus>§ 20</Explicatus>
        <Stk id="id868f48be-02d7-492d-a7e5-59aa0cf3fce0">
          <Explicatus>Stk. 1.</Explicatus>
          <Exitus>
            <Linea>
              <Char>Loven træder i kraft den 1. juli 1994.</Char>
            </Linea>
          </Exitus>
        </Stk>
        <Stk id="idfeb2ec02-e8be-45ab-95ad-c91ccb0fa3e0">
          <Explicatus>Stk. 2.</Explicatus>
          <Exitus>
            <Linea>
              <Char>(Udeladt)</Char>
            </Linea>
          </Exitus>
        </Stk>
        <Stk id="id7f878d0d-c73f-403c-99a6-fdbec255c5a6">
          <Explicatus>Stk. 3.</Explicatus>
          <Exitus>
            <Linea>
              <Char>Reglerne om lønindeholdelse efter §§ 1, 5-11, 12, nr. 2, 14, nr. 2, 18 og 19 finder også anvendelse på fordringer, der er forfaldne før lovens ikrafttræden.</Char>
            </Linea>
          </Exitus>
        </Stk>
      </IkraftCentreretParagraf>
    </Ikraft>
    <Ikraft id="idfbb96ee9-714b-4bf3-866a-f327b779fa68">
      <Exitus>
        <Linea>
          <Char>Lov nr. 1108 af 21. december 1994 om ændring af lov om støtte til miljøforbedrende investeringer i mindre landbrug m.v. og lov om ændring af lov om skattemæssige afskrivninger m.v.</Char>
        </Linea>
        <Nota id="idc33b582a-bdef-4722-ad68-377f536b6f3f">
          <Explicatus>8)</Explicatus>
          <Exitus>
            <Linea>
              <Char>Lovændringen vedrører ændring af § 2, stk. 1, § 10, stk. 2 og § 15, stk. 3, og indsættelse af § 2, stk. 3.</Char>
            </Linea>
          </Exitus>
        </Nota>
        <Linea>
          <Char>indeholder følgende ikrafttrædelsesbestemmelse:</Char>
        </Linea>
      </Exitus>
      <IkraftCentreretParagraf id="id050a00a9-9150-4f87-97f1-f332d7db7fc7">
        <Explicatus>§ 3</Explicatus>
        <Stk id="id4130b257-8924-4648-82ac-5ba8c1829375">
          <Exitus>
            <Linea>
              <Char>Landbrugs- og fiskeriministeren fastsætter tidspunktet for lovens ikrafttræden.</Char>
            </Linea>
            <Nota id="iddc987af0-b5b3-4837-8cb7-37caa5c91b91">
              <Explicatus>9)</Explicatus>
              <Exitus>
                <Linea>
                  <Char>Loven er trådt i kraft den 9. juni 1995, jf. bekendtgørelse nr. 343 af 1. juni 1995.</Char>
                </Linea>
              </Exitus>
            </Nota>
          </Exitus>
        </Stk>
      </IkraftCentreretParagraf>
    </Ikraft>
    <Ikraft id="id741b5a43-184a-46a8-99b0-722b7d2ded2e">
      <Exitus>
        <Linea>
          <Char>Lov nr. 430 af 6. juni 2005 om ændring af forskellige love og om ophævelse af lov om kommunalt samarbejde om opkrævning og inddrivelse (Konsekvensændringer som følge af lov om opkrævning og inddrivelse af visse fordringer – samlingen af inddrivelsen i Skatteministeriet)</Char>
        </Linea>
        <Nota id="id92547c8d-e9cc-4d14-a3d8-cb7d43bc7ca2">
          <Explicatus>10)</Explicatus>
          <Exitus>
            <Linea>
              <Char>Lovændringen vedrører ændring af § 20 a, stk. 1 og stk. 2, 1. pkt., og ophævelse af § 26 a, stk. 3, og § 21, stk. 5.</Char>
            </Linea>
          </Exitus>
        </Nota>
        <Linea>
          <Char>indeholder følgende ikrafttrædelsesbestemmelse:</Char>
        </Linea>
      </Exitus>
      <IkraftCentreretParagraf id="id6c868fc0-32d4-40fb-9e6b-2699163dbbe0">
        <Explicatus>§ 70</Explicatus>
        <Stk id="ide4db9d9a-926e-4013-9307-83be77e0ef29">
          <Explicatus>Stk. 1.</Explicatus>
          <Exitus>
            <Linea>
              <Char>Loven træder i kraft dagen efter bekendtgørelsen i Lovtidende.</Char>
            </Linea>
            <Nota id="idc322cc3e-0251-40da-97bc-b8fd2954f0b3">
              <Explicatus>11)</Explicatus>
              <Exitus>
                <Linea>
                  <Char>Loven er offentliggjort i Lovtidende den 7. juni 2005, og er trådt i kraft den 8. juni 2005.</Char>
                </Linea>
              </Exitus>
            </Nota>
          </Exitus>
        </Stk>
        <Stk id="id1061e056-87df-4c54-9600-9127c242145b">
          <Explicatus>Stk. 2.</Explicatus>
          <Exitus>
            <Linea>
              <Char>Loven har virkning fra den 1. november 2005, jf. dog stk. 3.</Char>
            </Linea>
          </Exitus>
        </Stk>
        <Stk id="idbf2d4d83-07b1-457b-b725-af295c806688">
          <Explicatus>Stk. 3.</Explicatus>
          <Exitus>
            <Linea>
              <Char>Afgørelser om inddrivelse, der inden den 1. oktober 2005 er påklaget til de hidtidige administrative klageinstanser, overgår til behandling i Landsskatteretten den 1. januar 2006, hvis de hidtidige klageinstanser ikke har færdigbehandlet klagen inden denne dato.</Char>
            </Linea>
          </Exitus>
        </Stk>
      </IkraftCentreretParagraf>
    </Ikraft>
    <Ikraft id="ide83c6140-08ea-4308-bbac-a6142edc3ba2">
      <Exitus>
        <Linea>
          <Char>Lov nr. 431 af 6. juni 2005 om ændring af forskellige love (Forenkling, harmonisering og objektivering af reglerne for inddrivelse af gæld til det offentlige m.v. samt mulighed for anvendelse af digitale lønsedler)</Char>
        </Linea>
        <Nota id="idcc6b0f46-60f3-4efb-b0fd-ba6c9949f554">
          <Explicatus>12)</Explicatus>
          <Exitus>
            <Linea>
              <Char>Lovændringen vedrører ændring af § 20 a, stk. 1, og indsættelse af § 20 b.</Char>
            </Linea>
          </Exitus>
        </Nota>
        <Linea>
          <Char>indeholder følgende ikrafttrædelsesbestemmelse:</Char>
        </Linea>
      </Exitus>
      <IkraftCentreretParagraf id="idcd53e030-f14c-4e29-812e-89c8441fba95">
        <Explicatus>§ 85</Explicatus>
        <Stk id="id4cd0883a-d067-489f-ba51-b50635239fdc">
          <Explicatus>Stk. 1.</Explicatus>
          <Exitus>
            <Linea>
              <Char>Loven træder i kraft den 1. november 2005, jf. dog stk. 2.</Char>
            </Linea>
          </Exitus>
        </Stk>
        <Stk id="id9bdce669-0f9b-4412-bbd1-8232bf77a275">
          <Explicatus>Stk. 2.</Explicatus>
          <Exitus>
            <Linea>
              <Char>(Udeladt)</Char>
            </Linea>
          </Exitus>
        </Stk>
      </IkraftCentreretParagraf>
    </Ikraft>
    <Ikraft id="id254e943e-2b4e-4b42-96fc-c67832b8fca3">
      <Exitus>
        <Linea>
          <Char>Lov nr. 1336 af 19. december 2008 om ændring af kildeskatteloven, opkrævningsloven, udpantningsloven og forskellige andre love (Konsekvensændringer som følge af lov om inddrivelse af gæld til det offentlige)</Char>
        </Linea>
        <Nota id="idd557a5e8-9dac-4514-aac0-417085f9f0ea">
          <Explicatus>13)</Explicatus>
          <Exitus>
            <Linea>
              <Char>Lovændringen vedrører ophævelse af §§ 20 a-20 b.</Char>
            </Linea>
          </Exitus>
        </Nota>
        <Linea>
          <Char>indeholder følgende ikrafttrædelsesbestemmelse:</Char>
        </Linea>
      </Exitus>
      <IkraftCentreretParagraf id="ida385a9d2-2535-4eb5-8710-fffeaa37d194">
        <Explicatus>§ 167</Explicatus>
        <Stk id="id30cfa813-5984-4fac-8de9-8948bcdd1ad3">
          <Explicatus>Stk. 1.</Explicatus>
          <Exitus>
            <Linea>
              <Char>Loven træder i kraft den 1. januar 2009, jf. dog stk. 2.</Char>
            </Linea>
            <Linea>
              <Char>§ 11 finder alene anvendelse på afgørelser om lønindeholdelse, der træffes efter lovens ikrafttræden.</Char>
            </Linea>
          </Exitus>
        </Stk>
        <Stk id="idc0f08e6e-fa40-4831-bcc2-37069620cff7">
          <Explicatus>Stk. 2.</Explicatus>
          <Exitus>
            <Linea>
              <Char>(Udeladt)</Char>
            </Linea>
          </Exitus>
        </Stk>
      </IkraftCentreretParagraf>
    </Ikraft>
  </DokumentIndhold>
  <UnderskriftGruppe id="id5c7d90ee-53d7-4105-bb88-f548c7733a1c">
    <UnderskriftStedDato id="id5c7d90ee-53d7-4105-bb88-f548c7733a1c" />
    <Underskriver id="id5c7d90ee-53d7-4105-bb88-f548c7733a1c" />
  </UnderskriftGruppe>
</Dokument>